cilly/__init__.py
cilly/analyzer.py
cilly/compiler.py
cilly/repl.py
cilly-0.1.4.dist-info/licenses/LICENSE
cilly-0.1.4.dist-info/METADATA
cilly-0.1.4.dist-info/WHEEL
cilly-0.1.4.dist-info/top_level.txt
cilly-0.1.4.dist-info/RECORD
